data/__init__.py
data/analysis.py
data/parser.py
data/storage.py
weather/__init__.py
weather/api.py
weather/conditions.py
weather/forecast.py
myweatherlib-0.5.dist-info/METADATA
myweatherlib-0.5.dist-info/WHEEL
myweatherlib-0.5.dist-info/top_level.txt
myweatherlib-0.5.dist-info/RECORD
