Metadata-Version: 2.1
Name: myweatherlib
Version: 0.5
Author: Patryk
Author-email: tryczek5@gmail.com
Classifier: Programming Language :: Python :: 3
Classifier: License :: OSI Approved :: MIT License
Classifier: Operating System :: OS Independent
Requires-Python: >=3.6
Requires-Dist: requests
